pkmodel_zxara/__init__.py
pkmodel_zxara/__main__.py
pkmodel_zxara/input.py
pkmodel_zxara/model.py
pkmodel_zxara/output.py
pkmodel_zxara/solver.py
pkmodel_zxara/tests/__init__.py
pkmodel_zxara/tests/test_model.py
pkmodel_zxara/tests/test_solver.py
pkmodel_zxara-1.3.0.dist-info/LICENSE
pkmodel_zxara-1.3.0.dist-info/WHEEL
pkmodel_zxara-1.3.0.dist-info/METADATA
pkmodel_zxara-1.3.0.dist-info/RECORD
